setup.py
graphique_client.egg-info/PKG-INFO
graphique_client.egg-info/SOURCES.txt
graphique_client.egg-info/dependency_links.txt
graphique_client.egg-info/requires.txt
graphique_client.egg-info/top_level.txt
graphiqueclient/__init__.py
graphiqueclient/client.py
graphiqueclient/errors.py
graphiqueclient/image.py
graphiqueclient/test_image.py