Metadata-Version: 1.0
Name: graphique-client
Version: 1.0
Summary: A Python client to Graphique
Home-page: https://github.com/amrhassan/graphique-client-python
Author: Amr Hassan
Author-email: amr.hassan@gmail.com
License: MIT
Platform: UNKNOWN
